withcd.py
withcd-1.0.2.dist-info/LICENSE
withcd-1.0.2.dist-info/METADATA
withcd-1.0.2.dist-info/WHEEL
withcd-1.0.2.dist-info/top_level.txt
withcd-1.0.2.dist-info/RECORD
