Metadata-Version: 2.1
Name: withcd
Version: 1.0.2
Summary: Change working directory utility compatible with with statements
Home-page: https://github.com/GabrieleMaurina/withcd
Author: Gabriele Maurina
Author-email: gabrielemaurina95@gmail.com
License: MIT
Platform: UNKNOWN
Classifier: Programming Language :: Python :: 3
Classifier: License :: OSI Approved :: MIT License
Classifier: Operating System :: OS Independent
Requires-Python: >=3.8
License-File: LICENSE
